nbcat/__init__.py
nbcat/enums.py
nbcat/exceptions.py
nbcat/image.py
nbcat/main.py
nbcat/markdown.py
nbcat/pager.py
nbcat/py.typed
nbcat/schemas.py
nbcat-1.0.0.dist-info/METADATA
nbcat-1.0.0.dist-info/WHEEL
nbcat-1.0.0.dist-info/entry_points.txt
nbcat-1.0.0.dist-info/licenses/LICENSE
nbcat-1.0.0.dist-info/RECORD
