Metadata-Version: 2.4
Name: nbcat
Version: 1.0.0
Summary: cat for jupyter notebooks
Project-URL: Homepage, https://github.com/akopdev/nbcat
Project-URL: Repository, https://github.com/akopdev/nbcat
Author-email: Akop Kesheshyan <devnull@akop.dev>
Maintainer-email: Akop Kesheshyan <devnull@akop.dev>
License: MIT License
License-File: LICENSE
Requires-Python: >=3.10
Requires-Dist: argcomplete
Requires-Dist: markdownify
Requires-Dist: pydantic
Requires-Dist: requests
Requires-Dist: rich
Requires-Dist: textual
Requires-Dist: textual-image[textual]
Provides-Extra: dev
Requires-Dist: pytest; extra == 'dev'
Requires-Dist: pytest-cov; extra == 'dev'
Requires-Dist: pytest-mock; extra == 'dev'
Requires-Dist: pytest-responses; extra == 'dev'
Requires-Dist: ruff; extra == 'dev'
